[
  // Vim navigation.
  {
    "key": "ctrl+h",
    "command": "workbench.action.navigateLeft"
  },
  {
    "key": "ctrl+l",
    "command": "workbench.action.navigateRight"
  },
  {
    "key": "ctrl+k",
    "command": "workbench.action.navigateUp"
  },
  {
    "key": "ctrl+j",
    "command": "workbench.action.navigateDown"
  },
  // Back/forward navigation.
  {
    "key": "cmd+[",
    "command": "workbench.action.navigateBack"
  },
  {
    "key": "cmd+]",
    "command": "workbench.action.navigateForward"
  },
  // Editor tab navigation.
  {
    "key": "ctrl+tab",
    "command": "workbench.action.nextEditor"
  },
  {
    "key": "ctrl+shift+tab",
    "command": "workbench.action.previousEditor"
  },
  {
    "key": "cmd+e",
    "command": "-actions.findWithSelection"
  },
  {
    "key": "cmd+e",
    "command": "workbench.action.showAllEditorsByMostRecentlyUsed"
  },
  // Show active file.
  {
    "key": "alt+f",
    "command": "workbench.files.action.showActiveFileInExplorer"
  },
  // Go to references.
  {
    "key": "shift+cmd+u",
    "command": "editor.action.goToReferences",
    "when": "editorHasReferenceProvider && editorTextFocus && !inReferenceSearchEditor && !isInEmbeddedEditor"
  },
  {
    "key": "shift+f12",
    "command": "-editor.action.goToReferences",
    "when": "editorHasReferenceProvider && editorTextFocus && !inReferenceSearchEditor && !isInEmbeddedEditor"
  },
  // Search Editor.
  {
    "key": "cmd+s",
    "command": "searchEditorApplyChanges.apply",
    "when": "inSearchEditor"
  },
  {
    "key": "alt+o",
    "command": "outline.focus"
  },
  // Move editor to above group.
  {
    "key": "ctrl+cmd+up",
    "command": "workbench.action.moveEditorToAboveGroup"
  },
  {
    "key": "ctrl+cmd+up",
    "command": "-notebook.cell.focusOutOutput",
    "when": "notebookEditorFocused"
  },
  {
    "key": "ctrl+cmd+up",
    "command": "-workbench.action.terminal.resizePaneUp",
    "when": "terminalFocus && terminalProcessSupported"
  },
  // Move editor to above group.
  {
    "key": "ctrl+cmd+down",
    "command": "workbench.action.moveEditorToBelowGroup"
  },
  {
    "key": "ctrl+cmd+down",
    "command": "-notebook.cell.focusInOutput",
    "when": "notebookCellHasOutputs && notebookEditorFocused"
  },
  {
    "key": "ctrl+cmd+down",
    "command": "-notebook.focusNextEditor",
    "when": "notebookEditorFocused && notebookOutputFocused"
  },
  {
    "key": "ctrl+cmd+down",
    "command": "-workbench.action.terminal.resizePaneDown",
    "when": "terminalFocus && terminalProcessSupported"
  },
  // Close editor group.
  {
    "key": "shift+cmd+w",
    "command": "workbench.action.closeEditorsAndGroup"
  },
  {
    "key": "shift+cmd+w",
    "command": "-workbench.action.closeWindow"
  },
  // Toggle case sensitivity.
  {
    "key": "alt+c",
    "command": "-gitlens.showQuickCommitFileDetails",
    "when": "editorTextFocus && !gitlens:disabled && config.gitlens.keymap == 'alternate'"
  },
  {
    "key": "alt+c",
    "command": "toggleSearchEditorCaseSensitive",
    "when": "inSearchEditor && searchInputBoxFocus"
  },
  {
    "key": "alt+cmd+c",
    "command": "-toggleSearchEditorCaseSensitive",
    "when": "inSearchEditor && searchInputBoxFocus"
  },
  {
    "key": "alt+c",
    "command": "workbench.action.terminal.toggleFindCaseSensitive",
    "when": "terminalFindFocused && terminalProcessSupported || terminalFocus && terminalProcessSupported"
  },
  {
    "key": "alt+cmd+c",
    "command": "-workbench.action.terminal.toggleFindCaseSensitive",
    "when": "terminalFindFocused && terminalProcessSupported || terminalFocus && terminalProcessSupported"
  },
  {
    "key": "alt+c",
    "command": "toggleFindCaseSensitive",
    "when": "editorFocus"
  },
  {
    "key": "alt+cmd+c",
    "command": "-toggleFindCaseSensitive",
    "when": "editorFocus"
  },
  {
    "key": "alt+c",
    "command": "toggleSearchCaseSensitive",
    "when": "searchViewletFocus && !fileMatchOrFolderMatchFocus"
  },
  {
    "key": "alt+cmd+c",
    "command": "-toggleSearchCaseSensitive",
    "when": "searchViewletFocus && !fileMatchOrFolderMatchFocus"
  },
  // Fugitive / Unimpaired.
  {
    "key": "alt+f5",
    "command": "-workbench.action.editor.nextChange",
    "when": "editorTextFocus"
  },
  {
    "key": "shift+alt+f5",
    "command": "-workbench.action.editor.previousChange",
    "when": "editorTextFocus"
  },
  {
    "key": "] c",
    "command": "workbench.action.editor.nextChange"
  },
  {
    "key": "[ c",
    "command": "workbench.action.editor.previousChange"
  }
]
